RobotFramework_DoIP/DoipKeywords.py
RobotFramework_DoIP/RobotFramework_DoIP.pdf
RobotFramework_DoIP/RobotFramework_DoIP.py
RobotFramework_DoIP/__init__.py
RobotFramework_DoIP/constants.py
RobotFramework_DoIP/version.py
robotframework_doip-0.1.6.dist-info/LICENSE
robotframework_doip-0.1.6.dist-info/METADATA
robotframework_doip-0.1.6.dist-info/WHEEL
robotframework_doip-0.1.6.dist-info/top_level.txt
robotframework_doip-0.1.6.dist-info/RECORD
