Metadata-Version: 2.1
Name: robotframework-doip
Version: 0.1.6
Summary: RobotFramework for DoIP Client
Home-page: https://github.com/test-fullautomation/robotframework-doip
Author: Hua Van Thong
Author-email: thong.huavan@vn.bosch.com
License: UNKNOWN
Platform: UNKNOWN
Classifier: Programming Language :: Python :: 3
Classifier: License :: OSI Approved :: Apache Software License
Classifier: Operating System :: OS Independent
Classifier: Development Status :: 4 - Beta
Classifier: Intended Audience :: Developers
Classifier: Topic :: Software Development
Requires-Python: >=3.0
License-File: LICENSE
